zugbruecke/__init__.py
zugbruecke/_server_.py
zugbruecke/core/__init__.py
zugbruecke/core/abc.py
zugbruecke/core/cache.py
zugbruecke/core/callback_client.py
zugbruecke/core/callback_server.py
zugbruecke/core/config.py
zugbruecke/core/const.py
zugbruecke/core/data.py
zugbruecke/core/dll_client.py
zugbruecke/core/dll_server.py
zugbruecke/core/errors.py
zugbruecke/core/interpreter.py
zugbruecke/core/lib.py
zugbruecke/core/log.py
zugbruecke/core/memory.py
zugbruecke/core/mempkg.py
zugbruecke/core/path.py
zugbruecke/core/routine_client.py
zugbruecke/core/routine_server.py
zugbruecke/core/rpc.py
zugbruecke/core/session.py
zugbruecke/core/session_client.py
zugbruecke/core/session_server.py
zugbruecke/core/typeguard.py
zugbruecke/core/wenv.py
zugbruecke/core/definitions/__init__.py
zugbruecke/core/definitions/base.py
zugbruecke/core/definitions/custom.py
zugbruecke/core/definitions/func.py
zugbruecke/core/definitions/memsync.py
zugbruecke/core/definitions/simple.py
zugbruecke/core/definitions/struct.py
zugbruecke/ctypes/__init__.py
zugbruecke/ctypes/util.py
zugbruecke/ctypes/wintypes.py
zugbruecke-0.2.1.dist-info/LICENSE
zugbruecke-0.2.1.dist-info/WHEEL
zugbruecke-0.2.1.dist-info/METADATA
zugbruecke-0.2.1.dist-info/RECORD
