Metadata-Version: 2.1
Name: zugbruecke
Version: 0.2.1
Summary: Calling routines in Windows DLLs from Python scripts running under Linux, MacOS or BSD
Keywords: ctypes,wine
Author-email: "Sebastian M. Ernst" <ernst@pleiszenburg.de>
Maintainer-email: "Sebastian M. Ernst" <ernst@pleiszenburg.de>
Requires-Python: >=3.7
Classifier: Development Status :: 3 - Alpha
Classifier: Intended Audience :: Developers
Classifier: Intended Audience :: Information Technology
Classifier: Intended Audience :: Science/Research
Classifier: Intended Audience :: System Administrators
Classifier: License :: OSI Approved :: GNU Lesser General Public License v2 (LGPLv2)
Classifier: Operating System :: MacOS
Classifier: Operating System :: POSIX :: BSD
Classifier: Operating System :: POSIX :: Linux
Classifier: Programming Language :: Python :: 3
Classifier: Programming Language :: Python :: 3.7
Classifier: Programming Language :: Python :: 3.8
Classifier: Programming Language :: Python :: 3.9
Classifier: Programming Language :: Python :: 3.10
Classifier: Programming Language :: Python :: 3.11
Classifier: Programming Language :: Python :: 3 :: Only
Classifier: Programming Language :: Python :: Implementation :: CPython
Classifier: Topic :: Scientific/Engineering
Classifier: Topic :: Software Development
Classifier: Topic :: System :: Operating System
Classifier: Topic :: System :: Operating System Kernels
Classifier: Topic :: Utilities
Requires-Dist: wenv >=0.5.1,<0.6.0
Requires-Dist: flit ; extra == "dev"
Requires-Dist: Jinja2 ; extra == "dev"
Requires-Dist: python-lsp-server[all] ; extra == "dev"
Requires-Dist: Sphinx ; extra == "dev"
Requires-Dist: sphinx_rtd_theme ; extra == "dev"
Requires-Dist: sphinx-autodoc-typehints ; extra == "dev"
Requires-Dist: myst-parser ; extra == "dev"
Requires-Dist: toml ; extra == "dev"
Requires-Dist: twine ; extra == "dev"
Requires-Dist: hypothesis ; extra == "test"
Requires-Dist: pytest<7.0 ; extra == "test"
Requires-Dist: coverage[toml] ; extra == "test"
Requires-Dist: pytest-cov ; extra == "test"
Requires-Dist: typeguard ; extra == "test"
Requires-Dist: numpy ; extra == "test"
Project-URL: Documentation, https://zugbruecke.readthedocs.io/en/latest/
Project-URL: Home, https://github.com/pleiszenburg/zugbruecke
Project-URL: Source, https://github.com/pleiszenburg/zugbruecke
Provides-Extra: dev
Provides-Extra: test
